mssh_copy_id-0.0.2.data/scripts/mssh-copy-id.py
mssh_copy_id-0.0.2.dist-info/DESCRIPTION.rst
mssh_copy_id-0.0.2.dist-info/METADATA
mssh_copy_id-0.0.2.dist-info/RECORD
mssh_copy_id-0.0.2.dist-info/WHEEL
mssh_copy_id-0.0.2.dist-info/entry_points.txt
mssh_copy_id-0.0.2.dist-info/metadata.json
mssh_copy_id-0.0.2.dist-info/top_level.txt
msshcopyid/__init__.py
msshcopyid/_version.py
